netbox_pve_sync/__init__.py
netbox_pve_sync-0.2.4.dist-info/licenses/LICENSE.txt
netbox_pve_sync-0.2.4.dist-info/METADATA
netbox_pve_sync-0.2.4.dist-info/WHEEL
netbox_pve_sync-0.2.4.dist-info/entry_points.txt
netbox_pve_sync-0.2.4.dist-info/top_level.txt
netbox_pve_sync-0.2.4.dist-info/RECORD
