Metadata-Version: 2.4
Name: netbox-pve-sync
Version: 0.2.4
Summary: Synchronize Proxmox Virtual Environment (PVE) information to a NetBox instance
Author-email: Aloïs Micard <alois@micard.lu>
Project-URL: Homepage, https://git.creekorful.cloud/creekorful/netbox-pve-sync
Project-URL: Issues, https://git.creekorful.cloud/creekorful/netbox-pve-sync/issues
Project-URL: Changelog, https://git.creekorful.cloud/creekorful/netbox-pve-sync/src/branch/main/Changelog.md
Classifier: Programming Language :: Python :: 3
Classifier: Operating System :: OS Independent
Requires-Python: >=3.8
License-File: LICENSE.txt
Requires-Dist: pynetbox>=7.4
Requires-Dist: proxmoxer>=2.2
Requires-Dist: requests>=2.32
Dynamic: license-file
